credit_scoring_model/VERSION
credit_scoring_model/__init__.py
credit_scoring_model/config.yml
credit_scoring_model/pipeline.py
credit_scoring_model/predict.py
credit_scoring_model/train_pipeline.py
credit_scoring_model/config/__init__.py
credit_scoring_model/config/core.py
credit_scoring_model/datasets/bank.csv
credit_scoring_model/datasets/xtest.csv
credit_scoring_model/datasets/xtrain.csv
credit_scoring_model/datasets/ytest.csv
credit_scoring_model/datasets/ytrain.csv
credit_scoring_model/processing/__init__.py
credit_scoring_model/processing/data_manager.py
credit_scoring_model/processing/validation.py
credit_scoring_model/trained_models/credit_scoring_model_output_v0.0.12.pkl
credit_scoring_model-0.0.12.dist-info/METADATA
credit_scoring_model-0.0.12.dist-info/WHEEL
credit_scoring_model-0.0.12.dist-info/top_level.txt
credit_scoring_model-0.0.12.dist-info/RECORD
